norm/__init__.py
norm/cached_property.py
norm/connection.py
norm/norm.py
norm/norm_mssql.py
norm/norm_myssql_connector.py
norm/norm_psycopg2.py
norm/norm_pymssql.py
norm/norm_sqlalchemy.py
norm/norm_sqlite3.py
norm/rows.py
norm-1.6.0.dist-info/LICENSE
norm-1.6.0.dist-info/WHEEL
norm-1.6.0.dist-info/METADATA
norm-1.6.0.dist-info/RECORD
