Metadata-Version: 2.1
Name: norm
Version: 1.6.0
Summary: Easy peasy SQL generation
License: MIT
Author: Justin Van Winkle
Author-email: justin.vanwinkle@gmail.com
Requires-Python: >=3.7,<4.0
Classifier: License :: OSI Approved :: MIT License
Classifier: Programming Language :: Python :: 3
Classifier: Programming Language :: Python :: 3.7
Classifier: Programming Language :: Python :: 3.8
Classifier: Programming Language :: Python :: 3.9
